telestream_cloud_qc/__init__.py
telestream_cloud_qc/api_client.py
telestream_cloud_qc/configuration.py
telestream_cloud_qc/rest.py
telestream_cloud_qc/api/__init__.py
telestream_cloud_qc/api/qc_api.py
telestream_cloud_qc/models/__init__.py
telestream_cloud_qc/models/alert.py
telestream_cloud_qc/models/audio_stream.py
telestream_cloud_qc/models/container.py
telestream_cloud_qc/models/data.py
telestream_cloud_qc/models/data_1.py
telestream_cloud_qc/models/extra_file.py
telestream_cloud_qc/models/inline_response_200.py
telestream_cloud_qc/models/inline_response_422.py
telestream_cloud_qc/models/job.py
telestream_cloud_qc/models/job_data.py
telestream_cloud_qc/models/job_details.py
telestream_cloud_qc/models/job_details_result.py
telestream_cloud_qc/models/job_details_synchonization_events.py
telestream_cloud_qc/models/job_details_synchronization_events.py
telestream_cloud_qc/models/jobs_collection.py
telestream_cloud_qc/models/media.py
telestream_cloud_qc/models/options.py
telestream_cloud_qc/models/project.py
telestream_cloud_qc/models/proxy.py
telestream_cloud_qc/models/summary.py
telestream_cloud_qc/models/synchronization_event.py
telestream_cloud_qc/models/template.py
telestream_cloud_qc/models/upload_file.py
telestream_cloud_qc/models/upload_session.py
telestream_cloud_qc/models/uploader.py
telestream_cloud_qc/models/video_stream.py
telestream_cloud_qc/models/video_upload_body.py
test/__init__.py
test/test_alert.py
test/test_audio_stream.py
test/test_container.py
test/test_data.py
test/test_data_1.py
test/test_extra_file.py
test/test_inline_response_200.py
test/test_inline_response_422.py
test/test_job.py
test/test_job_data.py
test/test_job_details.py
test/test_job_details_result.py
test/test_job_details_synchonization_events.py
test/test_job_details_synchronization_events.py
test/test_jobs_collection.py
test/test_media.py
test/test_options.py
test/test_project.py
test/test_proxy.py
test/test_qc_api.py
test/test_summary.py
test/test_synchronization_event.py
telestream_cloud_qc-2.0.3.1.dist-info/METADATA
telestream_cloud_qc-2.0.3.1.dist-info/WHEEL
telestream_cloud_qc-2.0.3.1.dist-info/top_level.txt
telestream_cloud_qc-2.0.3.1.dist-info/RECORD
