Metadata-Version: 2.1
Name: telestream-cloud-qc
Version: 2.0.3.1
Summary: Qc API
Home-page: https://github.com/telestream/telestream-cloud-python-sdk
Author: UNKNOWN
Author-email: cloudsupport@telestream.net
License: UNKNOWN
Keywords: Swagger,Qc API
Platform: UNKNOWN
Requires-Dist: urllib3 (>=1.15)
Requires-Dist: six (>=1.10)
Requires-Dist: certifi
Requires-Dist: python-dateutil
Requires-Dist: requests
